simple_dhcp_server/__init__.py
simple_dhcp_server/__main__.py
simple_dhcp_server/_version.py
simple_dhcp_server/dhcp.py
simple_dhcp_server/icon.icns
simple_dhcp_server/icon.ico
simple_dhcp_server/icon.png
simple_dhcp_server/linux-start-gui.sh
simple_dhcp_server/listener.py
simple_dhcp_server/macos.py
simple_dhcp_server/qt.py
simple_dhcp_server/tk.py
simple_dhcp_server/version.py
simple_dhcp_server-1.0.6.dist-info/METADATA
simple_dhcp_server-1.0.6.dist-info/WHEEL
simple_dhcp_server-1.0.6.dist-info/entry_points.txt
simple_dhcp_server-1.0.6.dist-info/licenses/LICENSE
simple_dhcp_server-1.0.6.dist-info/RECORD
