Metadata-Version: 2.4
Name: simple-dhcp-server
Version: 1.0.6
Summary: Very simple DHCP server written in Python.
Project-URL: Homepage, https://dhcp.quelltext.eu
Project-URL: Repository, https://github.com/niccokunzmann/simple_dhcp_server/
Project-URL: source_archive, https://github.com/niccokunzmann/simple_dhcp_server/archive/e1cee6064a9a0c23cc3d536c3a981a1a96159b1f.zip
Project-URL: Issues, https://github.com/niccokunzmann/simple_dhcp_server/issues
Project-URL: Documentation, https://dhcp.quelltext.eu/
Project-URL: Changelog, https://dhcp.quelltext.eu/changes
Author-email: Nicco Kunzmann <niccokunzmann@rambler.ru>
Maintainer-email: Nicco Kunzmann <niccokunzmann@rambler.ru>
License: The MIT License (MIT)
License-File: LICENSE
Keywords: LAN,dhcp,discover,logging,raspberry-pi
Classifier: Development Status :: 5 - Production/Stable
Classifier: License :: OSI Approved :: MIT License
Classifier: Operating System :: OS Independent
Classifier: Programming Language :: Python :: 3
Classifier: Topic :: Internet
Classifier: Topic :: System :: Logging
Classifier: Topic :: System :: Monitoring
Classifier: Topic :: System :: Networking
Classifier: Topic :: System :: Networking :: Monitoring
Classifier: Topic :: System :: Systems Administration
Classifier: Topic :: Utilities
Requires-Python: >=3.9
Provides-Extra: qt
Requires-Dist: pyside6; extra == 'qt'
Requires-Dist: pyyaml; extra == 'qt'
